{
  "$schema": "https://json-schema.org/draft/2020-12/schema",
  "$id": "https://schema.org/BackOrder.json",
  "$comment": "Autogenerated with schema-org-gen",
  "title": "Back Order",
  "media": {
    "type": "application/json;profile=https://schema.org/BackOrder"
  },
  "allOf": [
    {
      "$ref": "ItemAvailability.json"
    }
  ],
  "$defs": {
    "arrayOfBackOrders": {
      "type": "array",
      "items": {
        "$ref": "#"
      }
    },
    "possibleRef": {
      "oneOf": [
        {
          "$ref": "#"
        },
        {
          "type": "string",
          "format": "uri",
          "links": [
            {
              "rel": "full",
              "href": "{+$}"
            }
          ]
        }
      ]
    },
    "possibleRefArray": {
      "oneOf": [
        {
          "type": "string",
          "format": "uri",
          "links": [
            {
              "rel": "full",
              "href": "{+$}"
            }
          ]
        },
        {
          "type": "array",
          "items": {
            "$ref": "#/$defs/possibleRef"
          }
        }
      ]
    }
  }
}