{
  "$schema": "https://json-schema.org/draft/2020-12/schema",
  "$id": "https://schema.org/LymphaticVessel.json",
  "$comment": "Autogenerated with schema-org-gen",
  "title": "Lymphatic Vessel",
  "media": {
    "type": "application/json;profile=https://schema.org/LymphaticVessel"
  },
  "type": "object",
  "properties": {
    "originatesFrom": {
      "$ref": "Vessel.json#/$defs/possibleRef"
    },
    "regionDrained": {
      "$ref": "#/$defs/regionDrained"
    },
    "runsTo": {
      "$ref": "Vessel.json#/$defs/possibleRef"
    }
  },
  "$defs": {
    "arrayOfLymphaticVessels": {
      "type": "array",
      "items": {
        "$ref": "#"
      }
    },
    "possibleRef": {
      "oneOf": [
        {
          "$ref": "#"
        },
        {
          "type": "string",
          "format": "uri",
          "links": [
            {
              "rel": "full",
              "href": "{+$}"
            }
          ]
        }
      ]
    },
    "possibleRefArray": {
      "oneOf": [
        {
          "type": "string",
          "format": "uri",
          "links": [
            {
              "rel": "full",
              "href": "{+$}"
            }
          ]
        },
        {
          "type": "array",
          "items": {
            "$ref": "#/$defs/possibleRef"
          }
        }
      ]
    },
    "regionDrained": {
      "title": "Region Drained",
      "description": "The anatomical or organ system drained by this vessel; generally refers to a specific part of an organ.",
      "anyOf": [
        {
          "$ref": "AnatomicalSystem.json#/$defs/possibleRef"
        },
        {
          "$ref": "AnatomicalStructure.json#/$defs/possibleRef"
        }
      ]
    }
  }
}